{"activityId":22827816111,"typeKey":"cycling","name":"Langen (Hessen) Cycling","startTimeLocal":"2024-08-21 17:05:34","summary":{"duration":3177.441,"movingDuration":2910.0,"elapsedDuration":3177.441,"distance":18113.65,"calories":317.0,"bmrCalories":75.0,"averageHR":108.0,"maxHR":130.0,"minHR":63.0,"averageSpeed":5.701000213623047,"maxSpeed":9.432999610900879,"averageMovingSpeed":6.224622127362543,"elevationGain":243.04,"elevationLoss":286.17,"maxElevation":150.6,"minElevation":80.2,"avgElevation":123.72,"trainingEffect":1.2000000476837158,"anaerobicTrainingEffect":0.0,"trainingEffectLabel":"RECOVERY","aerobicTrainingEffectMessage":"MINOR_AEROBIC_BENEFIT_0","anaerobicTrainingEffectMessage":"NO_ANAEROBIC_BENEFIT_0","activityTrainingLoad":12.125564575195312,"waterEstimated":492.0,"averageTemperature":26.237278356633798,"maxTemperature":29.0,"minTemperature":25.0,"avgRespirationRate":24.600000381469727,"maxRespirationRate":29.530000686645508,"minRespirationRate":13.579999923706055},"cycling":{"averageBikeCadence":78.0,"maxBikeCadence":104.0},"laps":[{"lapIndex":1,"distance":5000.0,"duration":753.938,"movingDuration":740.0,"elapsedDuration":753.938,"averageSpeed":6.631999969482423,"maxSpeed":9.395999908447266,"averageHR":103.0,"maxHR":118.0,"calories":74.0,"elevationGain":19.45,"elevationLoss":68.89,"averageBikeCadence":80.0},{"lapIndex":2,"distance":5000.0,"duration":839.619,"movingDuration":772.0,"elapsedDuration":839.619,"averageSpeed":5.954999923706055,"maxSpeed":8.098999977111816,"averageHR":111.0,"maxHR":122.0,"calories":92.0,"elevationGain":48.97,"elevationLoss":57.44,"averageBikeCadence":81.0},{"lapIndex":3,"distance":5000.0,"duration":896.418,"movingDuration":810.0,"elapsedDuration":896.418,"averageSpeed":5.578000068664551,"maxSpeed":9.432999610900879,"averageHR":108.0,"maxHR":126.0,"calories":81.0,"elevationGain":85.34,"elevationLoss":74.47,"averageBikeCadence":78.0},{"lapIndex":4,"distance":3113.65,"duration":687.466,"movingDuration":588.0,"elapsedDuration":687.466,"averageSpeed":4.5289998054504395,"maxSpeed":9.079000473022461,"averageHR":112.0,"maxHR":130.0,"calories":69.0,"elevationGain":89.39,"elevationLoss":85.48,"averageBikeCadence":72.0}],"hrZones":[{"zone":1,"secs":1307.111,"floor":92},{"zone":2,"secs":1590.991,"floor":111},{"zone":3,"secs":24.0,"floor":129},{"zone":4,"secs":0.0,"floor":148},{"zone":5,"secs":0.0,"floor":166}]}