{"activityId":23079321238,"typeKey":"road_biking","name":"Wolfratshausen Road Cycling","startTimeLocal":"2026-05-31 03:36:25","summary":{"duration":25497.66,"movingDuration":25497.66,"elapsedDuration":39159.922,"distance":168045.7,"calories":5955.0,"bmrCalories":675.0,"averageSpeed":6.591000080108643,"maxSpeed":17.121999740600586,"averageMovingSpeed":6.590632320582112,"elevationGain":1648.0,"elevationLoss":1059.0,"maxElevation":1384.8,"minElevation":540.6,"avgElevation":791.42,"trainingEffect":0.10000000149011612,"anaerobicTrainingEffect":0.0,"trainingEffectLabel":"UNKNOWN","aerobicTrainingEffectMessage":"NO_AEROBIC_BENEFIT_18","anaerobicTrainingEffectMessage":"NO_ANAEROBIC_BENEFIT_0","activityTrainingLoad":1.3853607177734375,"waterEstimated":7032.0,"averageTemperature":19.0,"maxTemperature":27.0,"minTemperature":11.0},"cycling":{"beginPotentialStamina":100.0,"endPotentialStamina":69.0,"minAvailableStamina":69.0},"laps":[{"lapIndex":1,"distance":168045.7,"duration":25497.66,"movingDuration":25497.66,"elapsedDuration":39159.922,"averageSpeed":6.591000080108643,"maxSpeed":17.121999740600586,"calories":5955.0,"elevationGain":1648.0,"elevationLoss":1059.0}],"weather":{"tempF":57,"apparentTempF":57,"dewPointF":50,"humidity":77,"windSpeed":4,"windGust":null,"windDirection":"sw","desc":"Fair"}}