{"activityId":23421742490,"typeKey":"strength_training","name":"Krafttrai​ning","startTimeLocal":"2026-06-29 19:28:49","summary":{"duration":5209.703,"movingDuration":1981.394,"elapsedDuration":5214.669,"distance":0.0,"calories":486.0,"bmrCalories":138.0,"averageHR":109.0,"maxHR":137.0,"minHR":69.0,"averageSpeed":0.0,"averageMovingSpeed":0.0,"trainingEffect":1.2000000476837158,"anaerobicTrainingEffect":0.0,"trainingEffectLabel":"AEROBIC_BASE","aerobicTrainingEffectMessage":"MINOR_AEROBIC_BENEFIT_6","anaerobicTrainingEffectMessage":"NO_ANAEROBIC_BENEFIT_0","activityTrainingLoad":13.552444458007812,"moderateIntensityMinutes":56,"vigorousIntensityMinutes":0,"waterEstimated":990.0,"averageTemperature":31.977543186180423,"maxTemperature":33.0,"minTemperature":31.0},"laps":[{"lapIndex":1,"distance":0.0,"duration":5209.703,"movingDuration":1981.394,"elapsedDuration":5214.669,"averageSpeed":0.0,"averageHR":109.0,"maxHR":137.0,"calories":486.0}],"hrZones":[{"zone":1,"secs":2775.727,"floor":101},{"zone":2,"secs":978.017,"floor":121},{"zone":3,"secs":0.0,"floor":141},{"zone":4,"secs":0.0,"floor":161},{"zone":5,"secs":0.0,"floor":181}]}